odoo/addons/product_analytic_donation/README.rst
odoo/addons/product_analytic_donation/__init__.py
odoo/addons/product_analytic_donation/__manifest__.py
odoo/addons/product_analytic_donation/i18n/de.po
odoo/addons/product_analytic_donation/i18n/es.po
odoo/addons/product_analytic_donation/i18n/it.po
odoo/addons/product_analytic_donation/i18n/product_analytic_donation.pot
odoo/addons/product_analytic_donation/models/__init__.py
odoo/addons/product_analytic_donation/models/donation_line.py
odoo/addons/product_analytic_donation/readme/CONTRIBUTORS.rst
odoo/addons/product_analytic_donation/readme/DESCRIPTION.rst
odoo/addons/product_analytic_donation/readme/USAGE.rst
odoo/addons/product_analytic_donation/static/description/icon.png
odoo/addons/product_analytic_donation/static/description/index.html
odoo/addons/product_analytic_donation/tests/__init__.py
odoo/addons/product_analytic_donation/tests/test_donation.py
odoo14_addon_product_analytic_donation-14.0.1.0.1.dev11.dist-info/METADATA
odoo14_addon_product_analytic_donation-14.0.1.0.1.dev11.dist-info/WHEEL
odoo14_addon_product_analytic_donation-14.0.1.0.1.dev11.dist-info/top_level.txt
odoo14_addon_product_analytic_donation-14.0.1.0.1.dev11.dist-info/RECORD
